setup.cfg
setup.py
intstr/__init__.py
intstr.egg-info/PKG-INFO
intstr.egg-info/SOURCES.txt
intstr.egg-info/dependency_links.txt
intstr.egg-info/not-zip-safe
intstr.egg-info/top_level.txt