Metadata-Version: 1.0
Name: intstr
Version: 0.11
Summary: int encode to string & string decode to int , can use in url shorten with a auto incr id
Home-page: UNKNOWN
Author: zuroc
Author-email: zsp007@gmail.com
License: UNKNOWN
Platform: UNKNOWN
